RunningWiFi/__init__.py
RunningWiFi-1.dist-info/METADATA
RunningWiFi-1.dist-info/WHEEL
RunningWiFi-1.dist-info/top_level.txt
RunningWiFi-1.dist-info/RECORD
